fundb/__init__.py
fundb/json/__init__.py
fundb/json/jsonextendsclass.py
fundb/sqlalchemy/__init__.py
fundb/sqlalchemy/base.py
fundb/sqlalchemy/engine.py
fundb/sqlalchemy/table.py
funorm-1.0.3.dist-info/METADATA
funorm-1.0.3.dist-info/WHEEL
funorm-1.0.3.dist-info/top_level.txt
funorm-1.0.3.dist-info/RECORD
